[
    {
        "sentence": [
            "Long-term",
            "borehole",
            "monitoring",
            "system",
            "overview",
            "1",
            "Observatory",
            "string",
            "instruments",
            "6",
            "Data",
            "recording",
            "before",
            "DONET",
            "connection",
            "and",
            "future",
            "ROV",
            "operations",
            "11",
            "Acoustic",
            "modem",
            "12",
            "References"
        ],
        "ner": []
    },
    {
        "sentence": [
            "The",
            "long-term",
            "borehole",
            "monitoring",
            "system",
            "(LTBMS)",
            "deployed",
            "during",
            "International",
            "Ocean",
            "Discovery",
            "Program",
            "(IODP)",
            "Expedition",
            "380",
            "in",
            "Hole",
            "C0006G",
            "(Figure",
            "F1)",
            "is",
            "similar",
            "in",
            "design",
            "to",
            "the",
            "LTBMS",
            "observatories",
            "deployed",
            "during",
            "Integrated",
            "Ocean",
            "Drilling",
            "Program",
            "Expedition",
            "332",
            "in",
            "Hole",
            "C0002G",
            "(Expedition",
            "332",
            "Scientists,",
            "2011)",
            "and",
            "during",
            "IODP",
            "Expedition",
            "365",
            "in",
            "Hole",
            "C0010A",
            "(Kopf",
            "et",
            "al.,",
            "2017)."
        ],
        "ner": []
    },
    {
        "sentence": [
            "The",
            "LTBMS",
            "was",
            "designed",
            "for",
            "long-term",
            "observations",
            "of",
            "fault",
            "and",
            "crustal",
            "dynamics",
            "by",
            "monitoring",
            "multiple",
            "subseafloor",
            "parameters",
            "associated",
            "with",
            "ground",
            "motion,",
            "crustal",
            "deformation,",
            "and",
            "hydrogeological",
            "processes."
        ],
        "ner": []
    },
    {
        "sentence": [
            "Ground",
            "motion",
            "is",
            "monitored",
            "by",
            "a",
            "broadband",
            "seismometer",
            "and",
            "a",
            "tilt",
            "combo",
            "containing",
            "a",
            "three-component",
            "accelerometer,",
            "a",
            "three-component",
            "geophone,",
            "a",
            "tiltmeter,",
            "and",
            "a",
            "data",
            "logger."
        ],
        "ner": []
    },
    {
        "sentence": [
            "Crustal",
            "deformation",
            "is",
            "measured",
            "by",
            "a",
            "volumetric",
            "strainmeter."
        ],
        "ner": []
    },
    {
        "sentence": [
            "These",
            "three",
            "sets",
            "of",
            "instruments",
            "are",
            "combined",
            "in",
            "a",
            "downhole",
            "package",
            "that",
            "is",
            "cemented",
            "into",
            "place",
            "in",
            "an",
            "open",
            "hole",
            "below",
            "the",
            "casing."
        ],
        "ner": []
    },
    {
        "sentence": [
            "The",
            "cement",
            "provides",
            "good",
            "coupling",
            "with",
            "the",
            "formation",
            "and",
            "eliminates",
            "noise",
            "from",
            "potential",
            "borehole",
            "fluid",
            "flow."
        ],
        "ner": []
    },
    {
        "sentence": [
            "Except",
            "for",
            "the",
            "strainmeter,",
            "all",
            "of",
            "these",
            "instruments",
            "are",
            "mounted",
            "in",
            "an",
            "integrated",
            "instrument",
            "carrier",
            "(Figure",
            "F1)."
        ],
        "ner": []
    },
    {
        "sentence": [
            "To",
            "detect",
            "hydrogeological",
            "processes,",
            "a",
            "thermistor",
            "string",
            "and",
            "stand-alone",
            "heatflow",
            "(SAHF)",
            "temperature",
            "digitizer",
            "that",
            "measures",
            "borehole",
            "temperature",
            "at",
            "five",
            "depths",
            "from",
            "240",
            "to",
            "407",
            "meters",
            "below",
            "seafloor",
            "(mbsf)",
            "are",
            "connected",
            "to",
            "the",
            "tilt",
            "combo."
        ],
        "ner": []
    },
    {
        "sentence": [
            "The",
            "LTBMS",
            "in",
            "Hole",
            "C0006G",
            "also",
            "includes",
            "a",
            "pressure-sensing",
            "unit",
            "(PSU)",
            "with",
            "three",
            "pressure",
            "sensors."
        ],
        "ner": []
    },
    {
        "sentence": [
            "The",
            "third",
            "sensor",
            "is",
            "a",
            "reference",
            "that",
            "monitors",
            "seafloor",
            "pressure",
            "and",
            "temperature."
        ],
        "ner": []
    },
    {
        "sentence": [
            "Each",
            "instrument",
            "(strainmeter,",
            "broadband",
            "seismometer,",
            "and",
            "tilt",
            "combo)",
            "is",
            "connected",
            "by",
            "a",
            "communication/power",
            "sensor",
            "cable",
            "at",
            "the",
            "LTBMS",
            "CORK",
            "head",
            "that",
            "terminates",
            "in",
            "a",
            "Teledyne",
            "ODI",
            "underwater",
            "mateable",
            "connector",
            "(UMC)."
        ],
        "ner": []
    },
    {
        "sentence": [
            "The",
            "UMCs",
            "are",
            "mounted",
            "on",
            "the"
        ],
        "ner": []
    },
    {
        "sentence": [
            "LTBMS",
            "CORK",
            "head",
            "and",
            "lie",
            "just",
            "above",
            "hanging",
            "hooks",
            "for",
            "remotely",
            "operated",
            "vehicle",
            "(ROV)",
            "use."
        ],
        "ner": []
    },
    {
        "sentence": [
            "Figure",
            "F1",
            "shows",
            "a",
            "schematic",
            "of",
            "the",
            "LTBMS."
        ],
        "ner": []
    },
    {
        "sentence": [
            "Table",
            "T1",
            "summarizes",
            "the",
            "sampling",
            "rates",
            "and",
            "general",
            "specifications",
            "of",
            "all",
            "downhole",
            "instruments."
        ],
        "ner": []
    },
    {
        "sentence": [
            "Table",
            "T2",
            "and",
            "Figure",
            "F2",
            "describe",
            "the",
            "downhole",
            "positions",
            "of",
            "all",
            "instruments."
        ],
        "ner": []
    },
    {
        "sentence": [
            "The",
            "LTBMS",
            "instruments",
            "are",
            "listed",
            "here",
            "in",
            "detail",
            "from",
            "the",
            "bottom",
            "of",
            "the",
            "hole",
            "to",
            "the",
            "LTBMS",
            "CORK",
            "head."
        ],
        "ner": []
    },
    {
        "sentence": [
            "The",
            "PSU",
            "(on",
            "the",
            "CORK",
            "head)",
            "pressure",
            "ports",
            "are",
            "located",
            "in",
            "the",
            "lowermost",
            "portion",
            "of",
            "Hole",
            "C0006G."
        ],
        "ner": []
    },
    {
        "sentence": [
            "The",
            "PSU",
            "is",
            "equipped",
            "with",
            "three",
            "Paroscientific",
            "Digiquartz",
            "pressure",
            "transducers."
        ],
        "ner": []
    },
    {
        "sentence": [
            "Two",
            "of",
            "the",
            "transducers",
            "connect",
            "to",
            "$\\%$",
            "inch",
            "stainless",
            "steel",
            "tubing",
            "that",
            "terminates",
            "at",
            "two",
            "measurement",
            "points",
            "in",
            "the",
            "subseafloor,",
            "one",
            "ending",
            "in",
            "miniscreens",
            "and",
            "located",
            "below",
            "the",
            "cement",
            "(Pressure",
            "Port",
            "1",
            "[P1])",
            "and",
            "the",
            "other",
            "located",
            "within",
            "the",
            "cemented",
            "interval",
            "(Pressure",
            "Port",
            "2",
            "[P2])",
            "(Figure",
            "F2)."
        ],
        "ner": []
    },
    {
        "sentence": [
            "The",
            "third",
            "transducer",
            "(Pressure",
            "Port",
            "3",
            "[P3])",
            "measures",
            "pressure",
            "at",
            "the",
            "seafloor."
        ],
        "ner": []
    },
    {
        "sentence": [
            "The",
            "two",
            "subseafloor",
            "$\\%$",
            "inch",
            "hydraulic",
            "tubings",
            "are",
            "housed",
            "in",
            "a",
            "urethanecoated",
            "flatpack",
            "umbilical",
            "that",
            "connects",
            "the",
            "monitored",
            "intervals",
            "to",
            "the",
            "LTBMS",
            "CORK",
            "head",
            "(Figure",
            "F2)."
        ],
        "ner": []
    },
    {
        "sentence": [
            "A",
            "swellable",
            "packer",
            "and",
            "the",
            "cemented",
            "interval",
            "isolates",
            "the",
            "formation",
            "fluid",
            "and",
            "enables",
            "monitoring",
            "of",
            "in",
            "situ",
            "formation",
            "pressure",
            "once",
            "the",
            "response",
            "to",
            "drilling",
            "and",
            "open",
            "hole",
            "operations",
            "has",
            "dissipated."
        ],
        "ner": []
    },
    {
        "sentence": [
            "See",
            "Figure",
            "F3",
            "for",
            "a",
            "schematic",
            "of",
            "the",
            "PSU",
            "and",
            "tubing",
            "configuration."
        ],
        "ner": []
    },
    {
        "sentence": [
            "The",
            "first,",
            "lowermost",
            "monitoring",
            "interval",
            "(P1)",
            "is",
            "located",
            "at",
            "the",
            "bottom",
            "of",
            "the",
            "open",
            "borehole",
            "below",
            "the",
            "strainmeter,",
            "$8\\,\\mathrm{m}$",
            "beneath",
            "the",
            "cemented",
            "interval",
            "(Figures",
            "F1,",
            "F2)."
        ],
        "ner": []
    },
    {
        "sentence": [
            "Three",
            "1",
            "inch",
            "diameter",
            "miniscreens",
            "protect",
            "the",
            "$\\%$",
            "inch",
            "stainless",
            "steel",
            "hydraulic",
            "tubing",
            "from",
            "clogging",
            "and",
            "are",
            "connected",
            "to",
            "tubing",
            "by",
            "a",
            "single",
            "manifold",
            "(Figure",
            "F4)."
        ],
        "ner": []
    },
    {
        "sentence": [
            "The",
            "$\\%$",
            "inch",
            "tubing",
            "is",
            "connected",
            "to",
            "$\\%$",
            "inch",
            "tubing",
            "that",
            "passes"
        ],
        "ner": []
    },
    {
        "sentence": [
            "Figure",
            "F1."
        ],
        "ner": []
    },
    {
        "sentence": [
            "A."
        ],
        "ner": []
    },
    {
        "sentence": [
            "Main",
            "LTBMS",
            "components."
        ],
        "ner": []
    },
    {
        "sentence": [
            "$\\mathsf{P",
            "S",
            "U=}$",
            "pressure-sensing",
            "unit,",
            "$\\mathsf{U",
            "M",
            "C=}$",
            "underwater",
            "mateable",
            "connector,",
            "${\\mathsf{S",
            "A",
            "H",
            "F}}=$",
            "stand-alone",
            "heatflow."
        ],
        "ner": []
    },
    {
        "sentence": [
            "{\\mathsf{P3}}=$",
            "Pressure",
            "Ports",
            "1–3)",
            "and",
            "acoustic",
            "modem",
            "(Bay",
            "2)."
        ],
        "ner": []
    },
    {
        "sentence": [
            "through",
            "the",
            "strainmeter",
            "and",
            "to",
            "the",
            "instrument",
            "carrier",
            "above."
        ],
        "ner": []
    },
    {
        "sentence": [
            "The",
            "miniscreen",
            "configuration",
            "maximizes",
            "the",
            "azimuthal",
            "coverage",
            "of",
            "the",
            "borehole",
            "while",
            "minimizing",
            "the",
            "possibility",
            "of",
            "screen",
            "obstruction."
        ],
        "ner": []
    },
    {
        "sentence": [
            "The",
            "PSU",
            "is",
            "attached",
            "to",
            "a",
            "steel",
            "frame",
            "and",
            "mounted",
            "within",
            "Bay",
            "1",
            "of",
            "the",
            "LTBMS",
            "CORK",
            "head",
            "(Figures",
            "F1,",
            "F3)."
        ],
        "ner": []
    },
    {
        "sentence": [
            "The",
            "data",
            "logger",
            "in",
            "the",
            "PSU",
            "at",
            "the",
            "LTBMS",
            "CORK",
            "head",
            "can",
            "be",
            "accessed",
            "through",
            "an",
            "UMC",
            "with",
            "the",
            "same",
            "specifications",
            "as",
            "the",
            "set",
            "of",
            "three",
            "UMCs",
            "mounted",
            "in",
            "Bay",
            "2",
            "for",
            "the",
            "other",
            "instruments",
            "(see",
            "the",
            "following",
            "sections)."
        ],
        "ner": []
    },
    {
        "sentence": [
            "The",
            "pin",
            "layout",
            "of",
            "the",
            "Teledyne",
            "ODI",
            "connector",
            "is",
            "compatible",
            "to",
            "its",
            "three",
            "counterparts",
            "and",
            "therefore",
            "allows",
            "the",
            "ROV",
            "pilot",
            "to",
            "use",
            "the",
            "same",
            "interface",
            "for",
            "communication",
            "and",
            "data",
            "download."
        ],
        "ner": []
    },
    {
        "sentence": [
            "A",
            "series",
            "of",
            "pressure",
            "tests",
            "were",
            "performed",
            "in",
            "the",
            "laboratory",
            "and",
            "after",
            "the",
            "PSU",
            "was",
            "installed",
            "in",
            "Bay",
            "1",
            "at",
            "the",
            "LTBMS",
            "CORK",
            "head."
        ],
        "ner": []
    },
    {
        "sentence": [
            "During",
            "these",
            "tests,",
            "various",
            "problems",
            "were",
            "identified",
            "(see",
            "Table",
            "T4",
            "for",
            "troubleshooting",
            "during",
            "PSU",
            "testing)."
        ],
        "ner": []
    },
    {
        "sentence": [
            "All",
            "fittings",
            "and",
            "connections",
            "were",
            "checked",
            "and",
            "tightened",
            "prior",
            "to",
            "deployment,",
            "a",
            "procedure",
            "that",
            "needed",
            "to",
            "be",
            "completed",
            "multiple",
            "times",
            "before",
            "installation."
        ],
        "ner": []
    },
    {
        "sentence": [
            "A",
            "few",
            "days",
            "prior",
            "to",
            "deployment,",
            "the",
            "hydraulic",
            "tubing",
            "on",
            "the",
            "LTBMS",
            "CORK",
            "head",
            "was",
            "flushed,",
            "and",
            "the",
            "PSU",
            "was",
            "mounted",
            "on",
            "the",
            "LTBMS",
            "CORK",
            "head",
            "for",
            "further",
            "pressure",
            "tests",
            "to",
            "ensure",
            "that",
            "all",
            "of",
            "the",
            "plumbing",
            "and",
            "valves",
            "were",
            "configured",
            "correctly",
            "and",
            "pressuretight."
        ],
        "ner": []
    },
    {
        "sentence": [
            "First,",
            "flushing",
            "was",
            "performed",
            "with",
            "a",
            "hand",
            "pump",
            "(Figure",
            "F3)",
            "to",
            "check",
            "that",
            "water",
            "flowed",
            "through",
            "the",
            "correct",
            "pathways",
            "for",
            "each",
            "valve",
            "setting,",
            "and",
            "then",
            "each",
            "of",
            "the",
            "three",
            "hydraulic",
            "tubes",
            "were",
            "individually",
            "pressurized",
            "for",
            "testing."
        ],
        "ner": []
    },
    {
        "sentence": [
            "Once",
            "system",
            "integrity",
            "was",
            "confirmed,",
            "the",
            "tubing",
            "was",
            "depressurized",
            "and",
            "the",
            "tests",
            "were",
            "concluded."
        ],
        "ner": []
    },
    {
        "sentence": [
            "The",
            "strainmeter,",
            "cemented",
            "above",
            "the",
            "lowermost",
            "monitored",
            "pressure",
            "interval,",
            "was",
            "designed",
            "by",
            "Japan",
            "Agency",
            "for",
            "Marine-Earth",
            "Science",
            "and",
            "Technology",
            "(JAMSTEC)",
            "for",
            "deep-sea",
            "borehole",
            "installation."
        ],
        "ner": []
    },
    {
        "sentence": [
            "Figure",
            "F5",
            "shows",
            "a",
            "schematic",
            "of",
            "the",
            "LTBMS",
            "strainmeter,",
            "and",
            "Table",
            "T5",
            "lists",
            "instrument",
            "details."
        ],
        "ner": []
    },
    {
        "sentence": [
            "Similar",
            "to",
            "the",
            "Sacks-Evertson–",
            "type",
            "volumetric",
            "strainmeter,",
            "the",
            "LTBMS",
            "strainmeter",
            "measures",
            "the",
            "volume",
            "change",
            "of",
            "an",
            "oil-filled,",
            "cylindrical",
            "strain-sensing",
            "volume",
            "in",
            "response",
            "to",
            "the",
            "deformation",
            "of",
            "the",
            "surrounding",
            "formation",
            "(Sacks",
            "et",
            "al.,",
            "1971)."
        ],
        "ner": []
    },
    {
        "sentence": [
            "Formation",
            "deformation",
            "transmits",
            "to",
            "the",
            "sensing",
            "volume",
            "through",
            "the",
            "cement,",
            "which",
            "fills",
            "the",
            "annulus",
            "between",
            "the",
            "formation",
            "and",
            "the",
            "strainmeter."
        ],
        "ner": []
    },
    {
        "sentence": [
            "The",
            "strainmeter",
            "is",
            "$9.6\\,\\textrm{m}$",
            "long,",
            "including",
            "digitizer",
            "electronics",
            "and",
            "a",
            "transducer",
            "housing,",
            "chambers,",
            "joints,",
            "and",
            "the",
            "sensing",
            "volume",
            "$(\\sim\\!2.8$",
            "m)."
        ],
        "ner": []
    },
    {
        "sentence": [
            "It",
            "also",
            "incorporates",
            "tubing",
            "through",
            "its",
            "center",
            "so",
            "that",
            "cement",
            "can",
            "be",
            "pumped",
            "through",
            "the",
            "instrument,",
            "ultimately",
            "reaching",
            "the",
            "cement",
            "port",
            "on",
            "the",
            "bottom",
            "of",
            "the",
            "observatory",
            "for",
            "coupling",
            "to",
            "the",
            "formation."
        ],
        "ner": []
    },
    {
        "sentence": [
            "The",
            "strainmeter",
            "is",
            "designed",
            "to",
            "withstand",
            "ambient",
            "pressures",
            "as",
            "high",
            "as",
            "$70~\\mathrm{MPa}$",
            ",",
            "which",
            "is",
            "the",
            "maximum",
            "pressure",
            "the",
            "instrument",
            "may",
            "experience",
            "during",
            "transit",
            "through",
            "the",
            "water",
            "column",
            "to",
            "the",
            "borehole."
        ],
        "ner": []
    },
    {
        "sentence": [
            "While",
            "the",
            "strainmeter",
            "is",
            "being",
            "lowered",
            "from",
            "the",
            "ship,",
            "strain",
            "may",
            "exceed",
            "the",
            "full",
            "measurement",
            "range;",
            "therefore,",
            "a",
            "valve",
            "bypassing",
            "the",
            "bellows",
            "is",
            "installed",
            "and",
            "kept",
            "open",
            "to",
            "protect",
            "the",
            "sensor",
            "while",
            "the",
            "instrument",
            "is",
            "being",
            "deployed."
        ],
        "ner": []
    },
    {
        "sentence": [
            "After",
            "being",
            "cemented",
            "into",
            "position,",
            "a",
            "command",
            "issued",
            "through",
            "the",
            "acoustic",
            "modem",
            "will",
            "close",
            "the",
            "bypass",
            "valve",
            "and",
            "measurements",
            "will",
            "begin",
            "(see",
            "the",
            "following",
            "sections)."
        ],
        "ner": []
    },
    {
        "sentence": [
            "The",
            "bypass",
            "valve",
            "also",
            "opens",
            "automatically",
            "when",
            "the",
            "instrument",
            "measures",
            "strains",
            "outside",
            "of",
            "the",
            "full",
            "measurement",
            "range."
        ],
        "ner": []
    },
    {
        "sentence": [
            "By",
            "opening",
            "the",
            "valve,",
            "the",
            "bellows",
            "is",
            "recentered",
            "to",
            "zero,",
            "resetting",
            "accumulated",
            "strain."
        ],
        "ner": []
    },
    {
        "sentence": [
            "The",
            "valve",
            "is",
            "then",
            "closed",
            "to",
            "resume",
            "strain",
            "measurements."
        ],
        "ner": []
    },
    {
        "sentence": [
            "The",
            "position",
            "of",
            "the",
            "bellows",
            "indicates",
            "a",
            "strain",
            "change,",
            "which",
            "is",
            "recorded",
            "by",
            "a",
            "digitizer",
            "in",
            "the",
            "strainmeter."
        ],
        "ner": []
    },
    {
        "sentence": [
            "Strain",
            "data",
            "are",
            "transmitted",
            "uphole",
            "by",
            "a",
            "sensor",
            "cable",
            "terminating",
            "in",
            "a",
            "UMC."
        ],
        "ner": []
    },
    {
        "sentence": [
            "A",
            "Paroscientific",
            "pressure",
            "transducer",
            "is",
            "also",
            "connected",
            "to",
            "the",
            "strain-sensing",
            "volume,",
            "and",
            "its",
            "pressure",
            "reading",
            "is",
            "used",
            "to",
            "check",
            "the",
            "status",
            "of",
            "other",
            "components,",
            "including",
            "the",
            "bypass",
            "valve."
        ],
        "ner": []
    },
    {
        "sentence": [
            "A",
            "three-component",
            "accelerometer",
            "is",
            "also",
            "included",
            "within",
            "the",
            "strainmeter."
        ],
        "ner": []
    },
    {
        "sentence": [
            "A",
            "controller",
            "inside",
            "the",
            "strainmeter",
            "regulates",
            "the",
            "digitizing",
            "displacement",
            "of",
            "the",
            "bellows,",
            "valve",
            "position",
            "(open",
            "or",
            "closed),",
            "and",
            "acceleration."
        ],
        "ner": []
    },
    {
        "sentence": [
            "The",
            "cable",
            "transmits",
            "serial",
            "data",
            "and",
            "power",
            "(24–30",
            "V",
            "DC)",
            "to",
            "the",
            "strainmeter."
        ],
        "ner": []
    },
    {
        "sentence": [
            "Table",
            "T1."
        ],
        "ner": []
    },
    {
        "sentence": [
            "Long-term",
            "borehole",
            "monitoring",
            "system",
            "(LTBMS)",
            "instrument",
            "overview",
            "with",
            "sampling",
            "rates."
        ],
        "ner": []
    },
    {
        "sentence": [
            "$\\mathsf{P",
            "S",
            "U=}$",
            "pressure-sensing",
            "unit",
            "(P1–P3)."
        ],
        "ner": []
    },
    {
        "sentence": [
            "DONET",
            "$=$",
            "Dense",
            "Oceanfloor",
            "Network",
            "System",
            "for",
            "Earthquakes",
            "and",
            "Tsunamis."
        ],
        "ner": []
    },
    {
        "sentence": [
            "—",
            "$=$",
            "not",
            "applicable."
        ],
        "ner": []
    },
    {
        "sentence": [
            "Download",
            "table",
            "in",
            "CSV",
            "format."
        ],
        "ner": []
    },
    {
        "sentence": [
            "Vortex-induced",
            "vibration",
            "(VIV)",
            "is",
            "a",
            "common",
            "effect",
            "of",
            "the",
            "strong",
            "Kuroshio",
            "Current",
            "(Kitada",
            "et",
            "al.,",
            "2013),",
            "and",
            "operating",
            "in",
            "the",
            "current",
            "causes",
            "wear",
            "and",
            "damage",
            "to",
            "equipment",
            "and",
            "sensors."
        ],
        "ner": []
    },
    {
        "sentence": [
            "VIV",
            "exhibits",
            "a",
            "dominant",
            "frequency",
            "of",
            "$3{-}15\\",
            "\\mathrm{Hz}$",
            "and",
            "a",
            "maximum",
            "acceleration",
            "of",
            "2G."
        ],
        "ner": []
    },
    {
        "sentence": [
            "Vibration",
            "tests",
            "approximating",
            "these",
            "conditions",
            "were",
            "performed",
            "to",
            "confirm",
            "that",
            "the",
            "strainmeter",
            "design",
            "is",
            "capable",
            "of",
            "withstanding",
            "these",
            "vibrations",
            "during",
            "installation."
        ],
        "ner": []
    },
    {
        "sentence": [
            "These",
            "tests",
            "were",
            "applied",
            "to",
            "all",
            "strainmeter",
            "components",
            "and",
            "electronics."
        ],
        "ner": []
    },
    {
        "sentence": [
            "High-pressure",
            "tests",
            "(as",
            "high",
            "as",
            "$60\\",
            "\\mathrm{MPa}_{."
        ],
        "ner": []
    },
    {
        "sentence": [
            "}$",
            ")",
            "successfully",
            "showed",
            "that",
            "the",
            "valve,",
            "bellows,",
            "and",
            "sensor",
            "plumbing",
            "systems",
            "function",
            "correctly",
            "under",
            "pressure."
        ],
        "ner": []
    },
    {
        "sentence": [
            "Previous",
            "experience",
            "with",
            "deploying",
            "an",
            "LTBMS",
            "near",
            "the",
            "Nankai",
            "Trough",
            "in",
            "the",
            "strong",
            "Kuroshio",
            "Current",
            "demonstrated",
            "the",
            "need",
            "for",
            "a",
            "strong",
            "frame",
            "to",
            "shield",
            "the",
            "instruments",
            "from",
            "damaging",
            "forces."
        ],
        "ner": []
    },
    {
        "sentence": [
            "During",
            "Expedition",
            "380,",
            "however,",
            "the",
            "Kuroshio",
            "Current",
            "was",
            "never",
            "closer",
            "than",
            "$90\\;\\mathrm{km}$",
            "to",
            "Hole",
            "C0006G,",
            "leaving",
            "calm",
            "waters",
            "for",
            "a",
            "safer",
            "deployment",
            "and",
            "a",
            "speedy",
            "drilling",
            "program."
        ],
        "ner": []
    },
    {
        "sentence": [
            "Nonetheless,",
            "the",
            "instruments",
            "were",
            "housed",
            "within",
            "an",
            "H-beam–shaped",
            "instrument",
            "carrier",
            "designed",
            "to",
            "hold",
            "the",
            "delicate",
            "components",
            "and",
            "protect",
            "them",
            "during",
            "deployment."
        ],
        "ner": []
    },
    {
        "sentence": [
            "The",
            "carrier",
            "includes",
            "the",
            "borehole",
            "instruments,",
            "sensor",
            "cables,",
            "and",
            "hydraulic",
            "tubing."
        ],
        "ner": []
    },
    {
        "sentence": [
            "A",
            "$190\\,\\mathrm{\\mm}$",
            "diameter,",
            "$30\\,\\mathrm{\\mm}$",
            "thick",
            "flange",
            "at",
            "each",
            "end",
            "provides",
            "sufficient",
            "strength",
            "against",
            "bending",
            "and",
            "tension",
            "loading."
        ],
        "ner": []
    },
    {
        "sentence": [
            "Cables,",
            "hydraulic",
            "tubing,",
            "and",
            "the",
            "thermistor",
            "string",
            "(see",
            "following",
            "section)",
            "all",
            "pass",
            "through",
            "six",
            "preformed",
            "slits",
            "in",
            "each",
            "flange."
        ],
        "ner": []
    },
    {
        "sentence": [
            "Six",
            "M16",
            "high-tension",
            "bolts",
            "with",
            "self-locking",
            "nuts",
            "connect",
            "the",
            "flanges",
            "at",
            "each",
            "end."
        ],
        "ner": []
    },
    {
        "sentence": [
            "A",
            "schematic",
            "of",
            "the",
            "instrument",
            "carrier",
            "with",
            "installed",
            "instruments",
            "is",
            "shown",
            "in",
            "Figure",
            "F6."
        ],
        "ner": []
    },
    {
        "sentence": [
            "The",
            "orientation",
            "of",
            "the",
            "instruments",
            "is",
            "shown",
            "in",
            "Figure",
            "F7."
        ],
        "ner": []
    },
    {
        "sentence": [
            "The",
            "broadband",
            "seismometer",
            "(CMG3T)",
            "and",
            "tilt",
            "combo",
            "were",
            "installed",
            "on",
            "the",
            "instrument",
            "carrier",
            "using",
            "steel",
            "wrap-around",
            "bands",
            "with",
            "lock-nut",
            "fasteners",
            "(Figure",
            "F8)."
        ],
        "ner": []
    },
    {
        "sentence": [
            "All",
            "cables",
            "and",
            "hydraulic",
            "tubing",
            "and",
            "the",
            "thermistor",
            "string",
            "were",
            "connected",
            "to",
            "the",
            "instrument",
            "carrier",
            "using",
            "steel",
            "bands",
            "and",
            "plastic",
            "zip-ties."
        ],
        "ner": []
    },
    {
        "sentence": [
            "The",
            "CMG3T",
            "broadband",
            "seismometer",
            "installed",
            "in",
            "Hole",
            "C0006G",
            "is",
            "the",
            "same",
            "design",
            "as",
            "the",
            "one",
            "installed",
            "in",
            "Hole",
            "C0010A",
            "during",
            "Expedition",
            "365",
            "(Saffer",
            "et",
            "al.,",
            "2017)."
        ],
        "ner": []
    },
    {
        "sentence": [
            "Figure",
            "F8",
            "shows",
            "a",
            "schematic",
            "of",
            "the",
            "broadband",
            "seismometer."
        ],
        "ner": []
    },
    {
        "sentence": [
            "Table",
            "T6",
            "lists",
            "detailed",
            "information",
            "about",
            "the",
            "seismometer."
        ],
        "ner": []
    },
    {
        "sentence": [
            "The",
            "seismometer’s",
            "titanium",
            "housing",
            "contains",
            "three",
            "sensors",
            "that",
            "measure",
            "ground",
            "velocity",
            "on",
            "three",
            "orthogonal",
            "$(x-,$",
            "$y_{\\cdot}$",
            ",",
            "and",
            "$z\\cdot$",
            ")",
            "axes",
            "in",
            "the",
            "frequency",
            "range",
            "between",
            "1/360",
            "and",
            "$50\\",
            "\\mathrm{Hz}$",
            "."
        ],
        "ner": []
    },
    {
        "sentence": [
            "The",
            "seismometer",
            "is",
            "mounted",
            "near",
            "the",
            "bottom",
            "of",
            "the",
            "instrument",
            "carrier,",
            "which",
            "is",
            "cemented",
            "in",
            "the",
            "hole",
            "to",
            "ensure",
            "good",
            "coupling",
            "to",
            "the",
            "formation."
        ],
        "ner": []
    },
    {
        "sentence": [
            "Each",
            "sensor",
            "has",
            "a",
            "motorized",
            "leveling",
            "mechanism",
            "so",
            "that",
            "the",
            "sensors",
            "are",
            "functional",
            "within",
            "$4.5^{\\circ}$",
            "of",
            "tilt."
        ],
        "ner": []
    },
    {
        "sentence": [
            "Table",
            "T2."
        ],
        "ner": []
    },
    {
        "sentence": [
            "Long-term",
            "borehole",
            "monitoring",
            "system",
            "(LTBMS)",
            "instrument",
            "deployment",
            "depths."
        ],
        "ner": []
    },
    {
        "sentence": [
            "Download",
            "table",
            "in",
            "CSV",
            "format."
        ],
        "ner": []
    },
    {
        "sentence": [
            "Each",
            "sensor",
            "has",
            "a",
            "proof",
            "mass",
            "supported",
            "on",
            "a",
            "pivot,",
            "and",
            "each",
            "pivot",
            "is",
            "suspended",
            "by",
            "a",
            "leaf",
            "spring",
            "while",
            "measurements",
            "are",
            "active."
        ],
        "ner": []
    },
    {
        "sentence": [
            "The",
            "structurally",
            "weak",
            "pivot",
            "design",
            "assures",
            "very",
            "high",
            "sensitivity",
            "to",
            "ground",
            "motion."
        ],
        "ner": []
    },
    {
        "sentence": [
            "To",
            "protect",
            "these",
            "weak",
            "pivots",
            "from",
            "damage",
            "during",
            "transport,",
            "the",
            "proof",
            "masses",
            "are",
            "motion-locked."
        ],
        "ner": []
    },
    {
        "sentence": [
            "The",
            "tilt",
            "combo",
            "installed",
            "on",
            "the",
            "instrument",
            "carrier",
            "contains",
            "three",
            "components:",
            "the",
            "LILY",
            "tiltmeter,",
            "the",
            "tilt",
            "logger,",
            "and",
            "the",
            "SAHF",
            "temperature",
            "digitizer",
            "(Figure",
            "F9)."
        ],
        "ner": []
    },
    {
        "sentence": [
            "The",
            "SAHF",
            "temperature",
            "digitizer",
            "is",
            "connected",
            "to",
            "the",
            "thermistor",
            "string",
            "and",
            "is",
            "attached",
            "adjacent",
            "to",
            "the",
            "tilt",
            "combo",
            "on",
            "the",
            "instrument",
            "carrier."
        ],
        "ner": []
    },
    {
        "sentence": [
            "All",
            "instruments",
            "lie",
            "just",
            "above",
            "the",
            "broadband",
            "seismometer."
        ],
        "ner": []
    },
    {
        "sentence": [
            "Figure",
            "F2."
        ],
        "ner": []
    },
    {
        "sentence": [
            "Hole",
            "C0006G",
            "LTBMS."
        ],
        "ner": []
    },
    {
        "sentence": [
            "BRT",
            "$=$",
            "below",
            "rotary",
            "table,",
            "MSL",
            "$=$",
            "mean",
            "sea",
            "level."
        ],
        "ner": []
    },
    {
        "sentence": [
            "A",
            "schematic",
            "diagram",
            "of",
            "the",
            "tilt",
            "combo",
            "is",
            "shown",
            "in",
            "Figure",
            "F9,",
            "and",
            "Table",
            "T7",
            "contains",
            "specific",
            "information",
            "on",
            "each",
            "tilt",
            "combo",
            "instrument."
        ],
        "ner": []
    },
    {
        "sentence": [
            "The",
            "tilt",
            "combo",
            "measures",
            "both",
            "ground",
            "motion",
            "and",
            "crustal",
            "deformation,",
            "with",
            "crustal",
            "deformation",
            "detected",
            "by",
            "the",
            "LILY",
            "tiltmeter",
            "instrument."
        ],
        "ner": []
    },
    {
        "sentence": [
            "For",
            "ground",
            "motion,",
            "one",
            "titanium",
            "housing",
            "unit",
            "contains",
            "the",
            "three-component",
            "geophones,",
            "the",
            "three-component",
            "accelerometer",
            "electrical",
            "boards,",
            "a",
            "CPU",
            "board,",
            "an",
            "analog",
            "to",
            "digital",
            "(A/D)",
            "conversion",
            "board,",
            "a",
            "power",
            "supply",
            "board,",
            "and",
            "internal",
            "batteries."
        ],
        "ner": []
    },
    {
        "sentence": [
            "Signals",
            "from",
            "the",
            "three-component",
            "geophone",
            "and",
            "accelerometer",
            "are",
            "digitized",
            "by",
            "an",
            "A/D",
            "converter",
            "on",
            "the",
            "A/D",
            "conversion",
            "board."
        ],
        "ner": []
    },
    {
        "sentence": [
            "The",
            "A/D",
            "conversion",
            "board",
            "has",
            "a",
            "calibration",
            "circuit",
            "that",
            "transmits",
            "electrical",
            "pulses",
            "to",
            "the",
            "geophone."
        ],
        "ner": []
    },
    {
        "sentence": [
            "Each",
            "is",
            "connected",
            "to",
            "the",
            "CPU",
            "board",
            "through",
            "an",
            "electrical",
            "cable",
            "using",
            "dry-mate",
            "connectors."
        ],
        "ner": []
    },
    {
        "sentence": [
            "The",
            "tiltmeter,",
            "SAHF",
            "temperature",
            "digitizer,",
            "and",
            "accelerometer",
            "can",
            "individually",
            "be",
            "set",
            "to",
            "active",
            "or",
            "sleeping",
            "modes",
            "by",
            "switching",
            "electrical",
            "relays",
            "on",
            "the",
            "power",
            "supply",
            "board."
        ],
        "ner": []
    },
    {
        "sentence": [
            "All",
            "data",
            "are",
            "merged",
            "on",
            "the",
            "CPU",
            "board",
            "in",
            "standalone",
            "acquisition",
            "mode,",
            "in",
            "which",
            "data",
            "are",
            "stored",
            "to",
            "a",
            "mounted",
            "SD",
            "memory",
            "card."
        ],
        "ner": []
    },
    {
        "sentence": [
            "The",
            "CPU",
            "clock",
            "time",
            "can",
            "be",
            "synchronized",
            "to",
            "the",
            "GPS",
            "1",
            "pulse/s",
            "signal",
            "(Table",
            "T7)."
        ],
        "ner": []
    },
    {
        "sentence": [
            "Figure",
            "F3."
        ],
        "ner": []
    },
    {
        "sentence": [
            "A.",
            "PSU",
            "and",
            "hydraulic",
            "tubing,",
            "valves,",
            "and",
            "onboard",
            "pressure-testing",
            "layout",
            "(red",
            "box)."
        ],
        "ner": []
    },
    {
        "sentence": [
            "B.",
            "PSU",
            "installed",
            "in",
            "Bay",
            "1",
            "of",
            "the",
            "LTBMS",
            "CORK",
            "head,",
            "with",
            "hydraulic",
            "tubing",
            "configuration."
        ],
        "ner": []
    },
    {
        "sentence": [
            "Note",
            "the",
            "UMC",
            "port,",
            "valves",
            "for",
            "downhole",
            "tubing,",
            "and",
            "cylindrical",
            "pressure",
            "housing",
            "(enclosing",
            "data",
            "logger",
            "and",
            "pressure",
            "period",
            "counter",
            "[PPC]",
            "unit)."
        ],
        "ner": []
    },
    {
        "sentence": [
            "Table",
            "T3."
        ],
        "ner": []
    },
    {
        "sentence": [
            "Detailed",
            "pressure-sensing",
            "unit",
            "(PSU)",
            "specifications."
        ],
        "ner": []
    },
    {
        "sentence": [
            "P1–",
            "$\\cdot",
            "P2=$",
            "pressure",
            "ports,",
            "PPC1–PPC6",
            "$=$",
            "pressure",
            "period",
            "counter",
            "data",
            "channels,",
            "DONET",
            "$=$",
            "Dense",
            "Oceanfloor",
            "Network",
            "System",
            "for",
            "Earthquakes",
            "and",
            "Tsunamis."
        ],
        "ner": []
    },
    {
        "sentence": [
            "(Continued",
            "on",
            "next",
            "page.)"
        ],
        "ner": []
    },
    {
        "sentence": [
            "Download",
            "table",
            "in",
            "CSV",
            "format."
        ],
        "ner": []
    },
    {
        "sentence": [
            "Figure",
            "F4."
        ],
        "ner": []
    },
    {
        "sentence": [
            "3.5",
            "inch",
            "tubing",
            "bullnose",
            "at",
            "the",
            "bottom",
            "of",
            "the",
            "LTBMS",
            "assembly,",
            "with",
            "position",
            "and",
            "orientation",
            "of",
            "pressure",
            "port",
            "(P1)",
            "miniscreens."
        ],
        "ner": []
    },
    {
        "sentence": [
            "Additional",
            "sets",
            "of",
            "instruments",
            "were",
            "prepared",
            "as",
            "backups",
            "for",
            "the",
            "primary",
            "sets."
        ],
        "ner": []
    },
    {
        "sentence": [
            "These",
            "sensors",
            "included",
            "two",
            "sets",
            "of",
            "tilt",
            "logger",
            "pairs",
            "(Modules",
            "2",
            "and",
            "4),",
            "two",
            "sets",
            "of",
            "tiltmeters,",
            "and",
            "two",
            "sets",
            "of",
            "temperature",
            "digitizers",
            "(Numbers",
            "3",
            "and",
            "4)."
        ],
        "ner": []
    },
    {
        "sentence": [
            "A",
            "series",
            "of",
            "tests",
            "was",
            "performed",
            "on",
            "each",
            "tilt",
            "combo",
            "to",
            "ensure",
            "its",
            "functionality."
        ],
        "ner": []
    },
    {
        "sentence": [
            "Initial",
            "testing",
            "took",
            "place",
            "in",
            "the",
            "laboratory",
            "and",
            "involved",
            "hooking",
            "up",
            "the",
            "individual",
            "tilt",
            "combo",
            "components",
            "together",
            "in",
            "the",
            "configuration",
            "shown",
            "in",
            "Figure",
            "F9",
            "and",
            "powering",
            "them",
            "with",
            "an",
            "external",
            "power",
            "supply."
        ],
        "ner": []
    },
    {
        "sentence": [
            "The",
            "spare",
            "tilt",
            "combo",
            "encountered",
            "the",
            "same",
            "problem",
            "multiple",
            "times",
            "during",
            "initial",
            "testing:",
            "the",
            "instrument",
            "would",
            "suddenly",
            "stop",
            "recording",
            "after",
            "an",
            "unspecified",
            "amount",
            "of",
            "time."
        ],
        "ner": []
    },
    {
        "sentence": [
            "Troubleshooting",
            "revealed",
            "a",
            "loose",
            "wire",
            "in",
            "a",
            "connector,",
            "which",
            "was",
            "shorting",
            "out",
            "the",
            "tilt",
            "combo."
        ],
        "ner": []
    },
    {
        "sentence": [
            "When",
            "repaired,",
            "the",
            "spare",
            "began",
            "functioning",
            "normally."
        ],
        "ner": []
    },
    {
        "sentence": [
            "After",
            "initial",
            "testing,",
            "the",
            "primary",
            "tilt",
            "combo",
            "instruments",
            "were",
            "loaded",
            "into",
            "the",
            "instrument",
            "carrier,",
            "reconnected,",
            "and",
            "tested",
            "again."
        ],
        "ner": []
    },
    {
        "sentence": [
            "The",
            "thermistor",
            "string",
            "is",
            "designed",
            "for",
            "monitoring",
            "temperature",
            "in",
            "the",
            "borehole",
            "for",
            "long",
            "periods",
            "of",
            "time."
        ],
        "ner": []
    },
    {
        "sentence": [
            "The",
            "string",
            "contains",
            "five",
            "thermistors",
            "placed",
            "at",
            "intervals",
            "along",
            "an",
            "electrical",
            "cable,",
            "allowing",
            "for",
            "monitoring",
            "over",
            "$167~\\mathrm{m}$",
            "of",
            "the",
            "Hole",
            "C0006G",
            "LTBMS",
            "(Figure",
            "F2)."
        ],
        "ner": []
    },
    {
        "sentence": [
            "A",
            "schematic",
            "of",
            "the",
            "thermistor",
            "string",
            "and",
            "individual",
            "thermistor",
            "spacing",
            "are",
            "shown",
            "in",
            "Figure",
            "F10."
        ],
        "ner": []
    },
    {
        "sentence": [
            "Electrical",
            "wires",
            "are",
            "covered",
            "by",
            "a",
            "hydrolytically",
            "stable",
            "polyetherbased",
            "material,",
            "and",
            "the",
            "thermistors",
            "and",
            "connector",
            "are",
            "molded",
            "using",
            "the",
            "same",
            "material",
            "as",
            "the",
            "cable."
        ],
        "ner": []
    },
    {
        "sentence": [
            "The",
            "thermistor",
            "string",
            "is",
            "connected",
            "to",
            "the",
            "SAHF",
            "temperature",
            "digitizer",
            "and",
            "mounted",
            "within",
            "the",
            "instrument",
            "carrier."
        ],
        "ner": []
    },
    {
        "sentence": [
            "After",
            "the",
            "LTBMS",
            "was",
            "installed",
            "in",
            "Hole",
            "C0006G,",
            "the",
            "PSU",
            "began",
            "recording",
            "hydrostatic",
            "pressure",
            "(valves",
            "open",
            "to",
            "the",
            "ocean)",
            "using",
            "its",
            "own",
            "onboard",
            "battery",
            "power."
        ],
        "ner": []
    },
    {
        "sentence": [
            "The",
            "water",
            "depth",
            "for",
            "Hole",
            "C0006G",
            "exceeds",
            "the",
            "operation",
            "depth",
            "of",
            "the",
            "R/V",
            "Chikyu’s",
            "onboard",
            "ROV."
        ],
        "ner": []
    },
    {
        "sentence": [
            "With",
            "the",
            "lack",
            "of",
            "an",
            "on-site",
            "data",
            "recorder",
            "and",
            "power",
            "source,",
            "the",
            "tilt",
            "combo,",
            "strainmeter,",
            "and",
            "seismometer",
            "remained",
            "off-line",
            "until",
            "the",
            "LTBMS",
            "was",
            "connected",
            "to",
            "DONET."
        ],
        "ner": []
    },
    {
        "sentence": [
            "Time",
            "synchronization",
            "for",
            "the",
            "entire",
            "observatory",
            "was",
            "made",
            "upon",
            "connection",
            "to",
            "DONET,",
            "and",
            "power",
            "was",
            "provided",
            "to",
            "all",
            "sensors,",
            "allowing",
            "for",
            "the",
            "full",
            "suite",
            "of",
            "measurements",
            "to",
            "begin",
            "as",
            "of",
            "27",
            "March",
            "2018."
        ],
        "ner": []
    },
    {
        "sentence": [
            "The",
            "UMC",
            "for",
            "the",
            "PSU",
            "was",
            "accessible",
            "by",
            "the",
            "JAMSTEC",
            "ROV",
            "Hyper-Dolphin",
            "for",
            "pressure",
            "data",
            "recovery,",
            "as",
            "well",
            "as",
            "the",
            "UMCs",
            "for",
            "the",
            "other",
            "instruments",
            "for",
            "connection",
            "to",
            "DONET",
            "(Figure",
            "F1;",
            "note",
            "the",
            "hooks",
            "that",
            "lie",
            "just",
            "below",
            "the",
            "UMC",
            "ports",
            "in",
            "Bay",
            "2",
            "for",
            "ROV",
            "use)."
        ],
        "ner": []
    },
    {
        "sentence": [
            "An",
            "ROV",
            "platform",
            "attached",
            "to",
            "the",
            "LTBMS",
            "CORK",
            "head",
            "allows",
            "for",
            "easier",
            "ROV",
            "access",
            "during",
            "future",
            "underwater",
            "operations."
        ],
        "ner": []
    },
    {
        "sentence": [
            "Table",
            "T4."
        ],
        "ner": []
    },
    {
        "sentence": [
            "Pressure-sensing",
            "unit",
            "(PSU)",
            "troubleshooting."
        ],
        "ner": []
    },
    {
        "sentence": [
            "$^*=$",
            "possibly",
            "not",
            "the",
            "actual",
            "cause",
            "of",
            "the",
            "large",
            "pressure",
            "decrease",
            "seen",
            "in",
            "pressure",
            "tests."
        ],
        "ner": []
    },
    {
        "sentence": [
            "The",
            "loose",
            "hydraulic",
            "feed-through",
            "nut",
            "should",
            "be",
            "the",
            "primary",
            "reason;",
            "however,",
            "for",
            "completeness",
            "and",
            "future",
            "reference,",
            "we",
            "keep",
            "this",
            "item."
        ],
        "ner": []
    },
    {
        "sentence": [
            "$\\mathsf{N",
            "A}=$",
            "not",
            "applicable."
        ],
        "ner": []
    },
    {
        "sentence": [
            "Download",
            "table",
            "in",
            "CSV",
            "format."
        ],
        "ner": []
    },
    {
        "sentence": [
            "Figure",
            "F5."
        ],
        "ner": []
    },
    {
        "sentence": [
            "Strainmeter",
            "components",
            "and",
            "configuration."
        ],
        "ner": []
    },
    {
        "sentence": [
            "$\\mathsf{O",
            "D}=$",
            "outer",
            "diameter,",
            "XO",
            "$=$",
            "crossover."
        ],
        "ner": []
    },
    {
        "sentence": [
            "Table",
            "T5."
        ],
        "ner": []
    },
    {
        "sentence": [
            "Detailed",
            "strainmeter",
            "specifications."
        ],
        "ner": []
    },
    {
        "sentence": [
            "(Continued",
            "on",
            "next",
            "page.)"
        ],
        "ner": []
    },
    {
        "sentence": [
            "Download",
            "table",
            "in",
            "CSV",
            "format."
        ],
        "ner": []
    },
    {
        "sentence": [
            "Table",
            "T5",
            "(continued)."
        ],
        "ner": []
    },
    {
        "sentence": [
            "Figure",
            "F6."
        ],
        "ner": []
    },
    {
        "sentence": [
            "Instrument",
            "carrier."
        ],
        "ner": []
    },
    {
        "sentence": [
            "Figure",
            "F7."
        ],
        "ner": []
    },
    {
        "sentence": [
            "(A)",
            "Top",
            "and",
            "(B)",
            "bottom",
            "instrument",
            "carrier",
            "flanges."
        ],
        "ner": []
    },
    {
        "sentence": [
            "Note",
            "sensor",
            "cable",
            "placement",
            "and",
            "instrument",
            "orientation",
            "in",
            "the",
            "instrument",
            "carrier."
        ],
        "ner": []
    },
    {
        "sentence": [
            "Figure",
            "F8."
        ],
        "ner": []
    },
    {
        "sentence": [
            "Sensors",
            "and",
            "instrument",
            "carrier."
        ],
        "ner": []
    },
    {
        "sentence": [
            "A.",
            "Broadband",
            "seismometer."
        ],
        "ner": []
    },
    {
        "sentence": [
            "B.",
            "Tiltlogger."
        ],
        "ner": []
    },
    {
        "sentence": [
            "C.",
            "Orientation",
            "and",
            "position",
            "of",
            "sensors",
            "mounted",
            "on",
            "the",
            "instrument",
            "carrier."
        ],
        "ner": []
    },
    {
        "sentence": [
            "Table",
            "T6."
        ],
        "ner": []
    },
    {
        "sentence": [
            "Detailed",
            "broadband",
            "seismometer",
            "specifications."
        ],
        "ner": []
    },
    {
        "sentence": [
            "Download",
            "table",
            "in",
            "CSV",
            "format."
        ],
        "ner": []
    },
    {
        "sentence": [
            "Figure",
            "F9."
        ],
        "ner": []
    },
    {
        "sentence": [
            "Tilt",
            "combo",
            "component",
            "sensors."
        ],
        "ner": []
    },
    {
        "sentence": [
            "A/D",
            "$=$",
            "analog",
            "to",
            "digital."
        ],
        "ner": []
    },
    {
        "sentence": [
            "Table",
            "T7."
        ],
        "ner": []
    },
    {
        "sentence": [
            "Detailed",
            "tilt",
            "combo",
            "specifications."
        ],
        "ner": []
    },
    {
        "sentence": [
            "SAHF",
            "$=$",
            "stand-alone",
            "heat",
            "flow",
            "digitizer."
        ],
        "ner": []
    },
    {
        "sentence": [
            "(Continued",
            "on",
            "next",
            "page.)"
        ],
        "ner": []
    },
    {
        "sentence": [
            "Download",
            "table",
            "in",
            "CSV",
            "format."
        ],
        "ner": []
    },
    {
        "sentence": [
            "Figure",
            "F10."
        ],
        "ner": []
    },
    {
        "sentence": [
            "Thermistor",
            "string",
            "layout."
        ],
        "ner": []
    },
    {
        "sentence": [
            "An",
            "acoustic",
            "modem",
            "system",
            "temporarily",
            "replaced",
            "the",
            "ROV",
            "connection",
            "before",
            "connection",
            "to",
            "DONET,",
            "allowing",
            "communication",
            "with",
            "the",
            "installed",
            "LTBMS",
            "instruments",
            "through",
            "acoustic",
            "signals."
        ],
        "ner": []
    },
    {
        "sentence": [
            "The",
            "acoustic",
            "modem",
            "can",
            "control",
            "the",
            "electrical",
            "power",
            "fed",
            "to",
            "the",
            "borehole",
            "instruments",
            "and",
            "measure",
            "supplied/internal",
            "current",
            "and",
            "voltage."
        ],
        "ner": []
    },
    {
        "sentence": [
            "Furthermore,",
            "the",
            "acosic",
            "modem",
            "can",
            "obtain",
            "small",
            "data",
            "logs",
            "and",
            "instrument",
            "health",
            "information",
            "an",
            "can",
            "control",
            "the",
            "main",
            "functions",
            "of",
            "the",
            "downhole",
            "instruments",
            "(i.e.,",
            "turning",
            "sensors",
            "on/off,",
            "checking",
            "the",
            "conditions",
            "of",
            "the",
            "pivot",
            "masses",
            "within",
            "the",
            "seismometer,",
            "etc.)."
        ],
        "ner": []
    },
    {
        "sentence": [
            "Initial",
            "laboratory",
            "testing",
            "of",
            "acoustic",
            "communications",
            "proved",
            "successful,",
            "with",
            "each",
            "sensor",
            "responding",
            "promptly",
            "with",
            "appropriate",
            "data,",
            "functions,",
            "and",
            "sensor",
            "condition."
        ],
        "ner": []
    },
    {
        "sentence": [
            "Secondary",
            "communication",
            "tests",
            "during",
            "LTBMS",
            "preparation",
            "assured",
            "the",
            "acoustic",
            "modem’s",
            "functionality."
        ],
        "ner": []
    },
    {
        "sentence": [
            "A",
            "schematic",
            "diagram",
            "of",
            "the",
            "acoustic",
            "modem",
            "in",
            "the",
            "CORK",
            "head",
            "is",
            "shown",
            "in",
            "Figure",
            "F5,",
            "and",
            "Table",
            "T8",
            "contains",
            "specific",
            "information",
            "on",
            "the",
            "instrument."
        ],
        "ner": []
    },
    {
        "sentence": [
            "During",
            "installation,",
            "LTBMS",
            "sensor",
            "conditions",
            "were",
            "checked",
            "through",
            "acoustic",
            "modem",
            "communication."
        ],
        "ner": []
    },
    {
        "sentence": [
            "The",
            "receiver",
            "of",
            "the",
            "acoustic",
            "modem",
            "is",
            "connected",
            "by",
            "UMCs",
            "to",
            "the",
            "borehole",
            "instruments,",
            "and",
            "the",
            "transmitter",
            "of",
            "the",
            "acoustic",
            "modem",
            "was",
            "attached",
            "to",
            "the",
            "underwater",
            "TV."
        ],
        "ner": []
    },
    {
        "sentence": [
            "Table",
            "T8."
        ],
        "ner": []
    },
    {
        "sentence": [
            "Detailed",
            "acoustic",
            "modem",
            "specifications."
        ],
        "ner": []
    },
    {
        "sentence": [
            "UMC",
            "$=$",
            "underwater",
            "mateable",
            "connector."
        ],
        "ner": []
    },
    {
        "sentence": [
            "Download",
            "table",
            "in",
            "CSV",
            "format."
        ],
        "ner": []
    }
]